{
  "$schema": "https://schema.management.azure.com/schemas/2019-04-01/deploymentParameters.json#",
  "contentVersion": "1.0.0.0",
  "parameters": {
    "environment": {
      "value": "prod"
    },
    "acrName": {
      "value": "chatbotparkingprodacr"
    },
    "containerAppsEnvironmentName": {
      "value": "chatbot-parking-prod-env"
    },
    "adminContainerAppName": {
      "value": "chatbot-parking-prod-admin"
    },
    "mcpContainerAppName": {
      "value": "chatbot-parking-prod-mcp"
    },
    "adminApiToken": {
      "value": "replace-with-prod-admin-token"
    },
    "mcpApiToken": {
      "value": "replace-with-prod-mcp-token"
    },
    "vnetName": {
      "value": "chatbot-parking-prod-vnet"
    }
  }
}
