{
  "$schema": "https://schema.management.azure.com/schemas/2019-04-01/deploymentParameters.json#",
  "contentVersion": "1.0.0.0",
  "parameters": {
    "acrName": {
      "value": "chatbotparkingacr"
    },
    "containerAppsEnvironmentName": {
      "value": "chatbot-parking-env"
    },
    "adminContainerAppName": {
      "value": "chatbot-parking-admin"
    },
    "mcpContainerAppName": {
      "value": "chatbot-parking-mcp"
    },
    "deployCosmosDb": {
      "value": true
    },
    "cosmosAccountName": {
      "value": "chatbotparkingcosmosdev"
    },
    "cosmosDatabaseName": {
      "value": "chatbotParking"
    },
    "cosmosContainerName": {
      "value": "reservations"
    }
  }
}
